graphapi/__init__.py
graphapi/auth.py
graphapi/graph.py
graphapi/params.py
teamsgraphapi-0.0.5.dist-info/METADATA
teamsgraphapi-0.0.5.dist-info/WHEEL
teamsgraphapi-0.0.5.dist-info/licenses/LICENCE
teamsgraphapi-0.0.5.dist-info/RECORD
