Metadata-Version: 2.1
Name: TeamsGraphApi
Version: 0.0.5
Summary: wrapper for micorsoft teams graph api's
Project-URL: Homepage, https://github.com/Ajay7415/graphapi
Project-URL: Bug Tracker, https://github.com/Ajay7415/graphapi/issues
Author-email: Ajay Vishwakarma <ajay.vishwakarma@codiant.com>
License-File: LICENCE
Classifier: License :: OSI Approved :: MIT License
Classifier: Operating System :: OS Independent
Classifier: Programming Language :: Python :: 3
Requires-Python: >=3.8
Requires-Dist: requests==2.31.0
